mlcvzoo_darknet/__init__.py
mlcvzoo_darknet/configuration.py
mlcvzoo_darknet/darknetdatafile.py
mlcvzoo_darknet/model.py
mlcvzoo_darknet/py.typed
mlcvzoo_darknet-4.0.2.dist-info/LICENSE
mlcvzoo_darknet-4.0.2.dist-info/METADATA
mlcvzoo_darknet-4.0.2.dist-info/WHEEL
mlcvzoo_darknet-4.0.2.dist-info/RECORD
