Metadata-Version: 2.1
Name: mlcvzoo-darknet
Version: 4.0.2
Summary: MLCVZoo Darknet Package
Home-page: https://git.openlogisticsfoundation.org/silicon-economy/base/ml-toolbox/mlcvzoo-models/mlcvzoo-darknet
License: Open Logistics Foundation License v1.3
Author: Maximilian Otten
Author-email: maximilian.otten@iml.fraunhofer.de
Requires-Python: >=3.8,<4.0
Classifier: Development Status :: 5 - Production/Stable
Classifier: Intended Audience :: Developers
Classifier: License :: Other/Proprietary License
Classifier: Natural Language :: English
Classifier: Programming Language :: Python :: 3
Classifier: Programming Language :: Python :: 3.8
Classifier: Programming Language :: Python :: 3.9
Classifier: Programming Language :: Python :: 3.10
Classifier: Programming Language :: Python :: 3.11
Requires-Dist: attrs (>=20)
Requires-Dist: mlcvzoo_base (>=5.0,<6.0)
Requires-Dist: nptyping (>=2.0)
Requires-Dist: numpy (>=1.19.2,!=1.19.5)
Requires-Dist: opencv-contrib-python (>=4.5,!=4.5.5.64)
Requires-Dist: opencv-python (>=4.5,!=4.5.5.64)
Requires-Dist: related-mltoolbox (>=1.0,<2.0)
Requires-Dist: yaml-config-builder (>=8,<9)
Project-URL: Documentation, https://git.openlogisticsfoundation.org/silicon-economy/base/ml-toolbox/mlcvzoo-models/mlcvzoo-darknet/-/blob/main/documentation/index.adoc
Project-URL: Repository, https://git.openlogisticsfoundation.org/silicon-economy/base/ml-toolbox/mlcvzoo-models/mlcvzoo-darknet
